{
  "hash": "b6d912f7e60292be3065b514b3fcc652",
  "result": {
    "markdown": "---\ntitle: \"Lab 2: North Carolina Births\"\ncode-fold: false\nsidebar: false\nimage: images/births.jpeg\n---\n\n\n### Learning Objectives\n\n\nStudents will be able to:\n\n- Increase skill and comfort with basic data management and syntax in R \n- Create statistical graphics to answer questions about a data set\n- Review simulating the null distribution for sample proportions\n- Understand the basic methodology and syntax of the for loop\n- Carry out an entire test of significance for one proportion using simulations\n\n----\n\n### Readings\n\nTo prepare for this lab assignment read the following lecture notes\n\n\n1. [Logical Statements and Applications](/notes/06-logical-statements.qmd)\n2. [Introduction to for-loops](/notes/07-for-loops.qmd)\n3. [Sampling and Simulation](/notes/08-sampling_simulation.qmd)\n\n---\n\n### Required Data and Packages\n\nWe will continue to work with the NC data on births used in Lab 1\n\n\n::: {.cell}\n\n```{.r .cell-code}\nbirths <- read.csv('your path to births.csv')\n```\n:::\n\n\n\nThroughout the lab we will use the `mosaic` package\n\n\n::: {.cell}\n\n```{.r .cell-code}\nlibrary(mosaic)\n```\n:::\n\n\n---\n\n\n### Questions\n\n#### Question 1\n\nWhat are the names of the variables that indicate whether or not the mother smoked and the weight of the baby?\n\n\n#### Question 2\n\nIn addition to the variable that indicates whether or not the mother smoked, choose one numerical (quantitative) variable and one categorical variable that you think might also affect the weight of a baby. Explain why\n\n\n\n#### Question 3\n\nCreate a data frame that has only the variables `Gender, Premie, weight`, and `Apgar1`, and the observations for which the baby was not premature. Print out the first few rows using the `head()` function.\n\n\n#### Question 4\n\nCreate a data frame that has only the four variables you identified in Questions 1 and 2 and the observations for which the mother was a smoker. Print out the first few rows using the `head()` function\n\n\n\n#### Question 5\n\nReport the mean of\n\n(a) the weights of all babies.\n(b) the weights of those born to smoking mothers.\n(c) the weights of those born to non-smoking mothers.\n\nThe `sd()` function computes the standard deviation of the input. The syntax is identical to that of the `mean()` function\n\n#### Question 6\n\nReport the standard deviation of\n\n(a) the weights of all babies\n(b) the weights of those born to smoking mothers\n(c) the weights of those born to non-smoking mothers\n\n\n#### Question 7\n\nUsing `Births`, create two graphics that help answer this question: Does the birth weight of babies born to smoking mothers differ from those born to non-smoking mothers?\n\n*Note:* You are not limited to histograms. If you want, you can look into `dotPlot(), densityplot(), freqpolygon(), bwplot()`, and `mosaicplot()` for other types of plots to visualize data\n\n\n#### Question 8\n\nSet the seed to 3464 and simulate tossing 19 coins, where the probability of heads is 0.4 using `rflip()`\n\n\n#### Question 9\n\nSet the seed to 3464 and simulate 1000 repetitions of tossing 19 coins, where the probability of heads is 0.4. Save the output from this simulation, and print the first six lines from the saved data frame\n\n\n#### Question 10\n\nSet the seed to 9449 and choose 25 numbers out of the numbers from 1 to 1998, without replacement\n\n\n#### Question 11\n\nSet the seed to 9449 and simulate 19 coin flips using the `sample()` function, where the probability of heads (represented by 1) is 0.4. Print the proportion of heads obtained\n\n*Hint:* What would the `mean()` function do given the vector of coded coin flips?\n\n---\n\nFor **Questions 12-18** consider the following scenario:\n\nSuppose a researcher is testing to see if a basketball player can make free throws at a rate higher than the NBA average of 75%. The player is tested by shooting 10 free throws and makes 8 of them\n\n\n#### Question 12\n\nState the null and alternative hypotheses in words and in symbols\n\n\n#### Question 13\n\nSimulate the null distribution in R using the methods developed in this lab (i.e., the for loop\nand `sample()` function). Set the seed to 514. Do *not* use the `do() * rflip()` notation\n\n\n#### Question 14\n\nCreate a plot of the null distribution you simulated in Question 13\n\n\n#### Question 15\n\nCompute the (approximate) p-value based on your simulation\n\n\n#### Question 16\n\n\nCompute the value of the standardized statistic ($z$-statistic) based on the standard deviation of the null distribution you simulated in Question 13\n\n#### Question 17\n\nState your conclusion based on the strength of evidence, in context\n\n\n#### Question 18\n\n\nSuppose the player instead had made all 10 shots. Using the same simulation results from Question 13, state your conclusion about the strength of evidence with a significance level of 0.05. Can you think of any limitation(s) to the researcher’s study? Explain\n",
    "supporting": [],
    "filters": [
      "rmarkdown/pagebreak.lua"
    ],
    "includes": {},
    "engineDependencies": {},
    "preserve": {},
    "postProcess": true
  }
}